trmd/__init__.py
trmd/main.py
trmd-0.1.30.dist-info/METADATA
trmd-0.1.30.dist-info/WHEEL
trmd-0.1.30.dist-info/entry_points.txt
trmd-0.1.30.dist-info/licenses/LICENSE
trmd-0.1.30.dist-info/RECORD
