Metadata-Version: 2.4
Name: trmd
Version: 0.1.30
Summary: Translate Markdown using OpenAI
Project-URL: Homepage, https://github.com/rioriost/homebrew-trmd
Project-URL: Issues, https://github.com/rioriost/homebrew-trmd/issues
Author-email: Rio Fujita <rifujita@microsoft.com>
License: MIT License
License-File: LICENSE
Requires-Python: >=3.13
Requires-Dist: openai>=2.15.0
